Metadata-Version: 2.1
Name: sozlukpy
Version: 0.0.7
Summary: A basic Turkish dictionary
Home-page: https://gihtub.com/Meinos10/sozlukpy
Author: Emre
Author-email: E.tmen2023@gmail.com
License: MIT
Keywords: sozlukpy,sozlukpython,sozluk,sozluk-python,sozluk-py
Requires: requests
License-File: LICENSE
